[{"fname":"add animation for line.md","mtime":1709816423818.6792},{"fname":"add bound by arrow.md","mtime":1705907020789.4937},{"fname":"add bound.md","mtime":1705907020789.4937},{"fname":"add bulleted number.md","mtime":1708324145061.629},{"fname":"add collapse by line.md","mtime":1705907020789.4937},{"fname":"add detial - detail.md","mtime":1705773038904.4233},{"fname":"add detial - target.md","mtime":1705773038905.4236},{"fname":"add elements appear by line.md","mtime":1708919956166.2175},{"fname":"add fixed and dragable for line.md","mtime":1705650543305.669},{"fname":"add fixed length.md","mtime":1717243362564.875},{"fname":"add fixed.md","mtime":1705650543305.669},{"fname":"add gradient.md","mtime":1705650543305.669},{"fname":"add highlight link.md","mtime":1709090850008.8142},{"fname":"add hover by arrow.md","mtime":1705907020789.4937},{"fname":"add hover.md","mtime":1705907020789.4937},{"fname":"add image server.md","mtime":1709643448592.3684},{"fname":"add image to anki.md","mtime":1705650543305.669},{"fname":"add image to eagle.md","mtime":1708403993789.5952},{"fname":"add indent for text.md","mtime":1705907020789.4937},{"fname":"add layer.md","mtime":1705650543305.669},{"fname":"add left brace.md","mtime":1705650543305.669},{"fname":"add left brace.svg","mtime":1702528910914.6995},{"fname":"Add list continue.md","mtime":1705650543305.669},{"fname":"add measure.md","mtime":1707418465528.2654},{"fname":"add mermaid svg.md","mtime":1705907020789.4937},{"fname":"add mind map.md","mtime":1705907020789.4937},{"fname":"Add order list.md","mtime":1705650543305.669},{"fname":"Add order list.svg","mtime":1702529207009.8008},{"fname":"add outline level - string.md","mtime":1705650543305.669},{"fname":"add outline level - suggester.md","mtime":1705650543306.779},{"fname":"add partial bold.md","mtime":1705650543306.779},{"fname":"add partial color.md","mtime":1708403993789.5952},{"fname":"add reminder to todo list.md","mtime":1705650543306.779},{"fname":"add right brace.md","mtime":1705650543306.779},{"fname":"add right brace.svg","mtime":1702528954558.592},{"fname":"add shadow.md","mtime":1712658646172.0967},{"fname":"add text containers.md","mtime":1705907020789.4937},{"fname":"Add unorder list.md","mtime":1705650543306.779},{"fname":"Add unorder list.svg","mtime":1702529223758.9866},{"fname":"add wave drom.md","mtime":1705650543306.779},{"fname":"add wrapper.md","mtime":1705650543306.779},{"fname":"add zoomHide.md","mtime":1705650543306.779},{"fname":"autorun-addElementsFromPasteOrLibrary_Hook.md","mtime":1708322599013.3325},{"fname":"autorun-afterTransformElementsHook.md","mtime":1707929553998.0073},{"fname":"autorun-binding.md","mtime":1708608741628.4355},{"fname":"autorun-deleteSelectedElementsHook.md","mtime":1708921368666.3965},{"fname":"autorun-dragSelectedElementsHook.md","mtime":1711122179655.983},{"fname":"autorun-drawElementFromCanvasHook.md","mtime":1709660698758.8455},{"fname":"autorun-drawElementOnCanvasHook.md","mtime":1721038817235.15},{"fname":"autorun-generateElementCanvasHook.md","mtime":1705650543306.779},{"fname":"autorun-generateRoughOptionsHook.md","mtime":1705918590567.9277},{"fname":"autorun-handleCanvasPointerMove_Hook.md","mtime":1717243362564.875},{"fname":"autorun-handleCanvasPointerUp_Hook.md","mtime":1709090850010.3171},{"fname":"autorun-handleLinearElementOnPointerDownHook.md","mtime":1705650543306.779},{"fname":"autorun-handlePointDraggingHook.md","mtime":1717243362564.875},{"fname":"autorun-handleTextWysiwygHook.md","mtime":1705650543306.779},{"fname":"autorun-handleWheelHook.md","mtime":1708608741653.6465},{"fname":"autorun-maybeBindLinearElement_Hook.md","mtime":1721038817234.5767},{"fname":"autorun-onKeyDownHook.md","mtime":1711122179655.983},{"fname":"autorun-onLinkHook.md","mtime":1707929553998.0073},{"fname":"autorun-onPasteHook.md","mtime":1709713135535.9417},{"fname":"autorun-onPointerDownHook.md","mtime":1713974394265.8882},{"fname":"autorun-renderCustomDocument.md","mtime":1712658757809.4656},{"fname":"autorun-renderElementHook.md","mtime":1707928507897.8857},{"fname":"autorun-renderElementToSvg_Hook.md","mtime":1707928515233.9883},{"fname":"autorun-renderStaticSceneHook.md","mtime":1705650543306.779},{"fname":"autorun-replaceAllElementsHook.md","mtime":1705650543306.779},{"fname":"autorun-TextHook.md","mtime":1721038817234.5767},{"fname":"autorun-updateBoundPoint_Hook.md","mtime":1708608742118.8025},{"fname":"autorun-updateSceneHook.md","mtime":1707401532804.593},{"fname":"autorun-wrapTextHook.md","mtime":1717243362564.875},{"fname":"autorun-zoomToFitWrapper.md","mtime":1707929553998.0073},{"fname":"autorun-_renderInteractiveScene_Hook.md","mtime":1721038817234.5767},{"fname":"change slide line.md","mtime":1705907020789.4937},{"fname":"clear customData.md","mtime":1705650543307.7893},{"fname":"clear detail pos.md","mtime":1717243362671.3838},{"fname":"clear ea Mindmap.md","mtime":1705426170924.1086},{"fname":"close add image server.md","mtime":1705650543307.7893},{"fname":"Connect elements sequence by x.md","mtime":1705917158670.2769},{"fname":"Connect elements sequence by y.md","mtime":1705907020789.4937},{"fname":"Connect elements_by_x.md","mtime":1705907020789.4937},{"fname":"Connect elements_by_y.md","mtime":1705907020789.4937},{"fname":"convert connection shape to elbow.md","mtime":1709197684520.1338},{"fname":"convert latex in text.md","mtime":1705650543307.7893},{"fname":"convert latex in text.svg","mtime":1702459819760.3896},{"fname":"convert latex in text2.svg","mtime":1702455868307.4402},{"fname":"convert line to Right-angle.md","mtime":1709197684521.1355},{"fname":"convert text to echarts.md","mtime":1707392712724.2236},{"fname":"Convert text to reminder.md","mtime":1705907020789.4937},{"fname":"convert to shape (iink).md","mtime":1705650543307.7893},{"fname":"copy customData.md","mtime":1711122179655.983},{"fname":"copy elements text as single text.md","mtime":1705907020789.4937},{"fname":"cover text by text.md","mtime":1705650543307.7893},{"fname":"delete shape cache.md","mtime":1705650543307.7893},{"fname":"edit custom data.md","mtime":1705650543307.7893},{"fname":"export mindmap to md.md","mtime":1707401532804.593},{"fname":"fit equation size to font size.md","mtime":1705650543307.7893},{"fname":"follow.md","mtime":1705907020789.4937},{"fname":"follow_inv.md","mtime":1709815857844.6543},{"fname":"font bold.md","mtime":1705907020789.4937},{"fname":"font weight.md","mtime":1709643448592.3684},{"fname":"generate shape grid - hexagon.md","mtime":1705650543307.7893},{"fname":"generate shape grid.md","mtime":1705650543307.7893},{"fname":"generate table.md","mtime":1705650543307.7893},{"fname":"get element id to clipboard.md","mtime":1705650543307.7893},{"fname":"get file and area.md","mtime":1709090850010.3171},{"fname":"get largest element id.md","mtime":1705650543307.7893},{"fname":"highlight image.md","mtime":1705650543307.7893},{"fname":"highlight text by editable.md","mtime":1705907020790.7422},{"fname":"highlight text.md","mtime":1705907020790.7422},{"fname":"highlight text.svg","mtime":1684728656000},{"fname":"highlight text3.md","mtime":1705907020790.7422},{"fname":"Horizontal alignment.md","mtime":1705650543307.7893},{"fname":"Horizontal distribution.md","mtime":1705907020790.7422},{"fname":"Horizontal distribution.svg","mtime":1701690064976.635},{"fname":"increase size.md","mtime":1705907020790.7422},{"fname":"insert echarts.md","mtime":1707392712724.2236},{"fname":"insert image from ex link.md","mtime":1705907020790.7422},{"fname":"insert image from file area.md","mtime":1705650543307.7893},{"fname":"insert vertical space with width.md","mtime":1705650543307.7893},{"fname":"insert vertical space.md","mtime":1705650543307.7893},{"fname":"load more library.md","mtime":1705907020790.7422},{"fname":"mark as code.md","mtime":1712658646172.0967},{"fname":"Mindmap format2.md","mtime":1711122179655.983},{"fname":"Open file by default app.md","mtime":1705907020790.7422},{"fname":"paste text with containers - single.md","mtime":1705907020790.7422},{"fname":"paste text with containers.md","mtime":1705907020790.7422},{"fname":"reduce size.md","mtime":1705907020790.7422},{"fname":"remove animation.md","mtime":1709816423818.6792},{"fname":"remove shadow.md","mtime":1706064917450.5686},{"fname":"replace mindmap node.md","mtime":1708608742117.7993},{"fname":"resize images in same width.md","mtime":1705650543307.7893},{"fname":"return click link pos.md","mtime":1705907020790.7422},{"fname":"run code from text of element.md","mtime":1706791427916.3862},{"fname":"save pos.md","mtime":1705650543308.7961},{"fname":"search then select.md","mtime":1705650543308.7961},{"fname":"select by script.md","mtime":1705907020790.7422},{"fname":"select text elements.md","mtime":1705650543308.7961},{"fname":"Set angle.md","mtime":1705916413562.238},{"fname":"Set arrow type.md","mtime":1705916413562.238},{"fname":"Set bulleted number index.md","mtime":1708322599013.3325},{"fname":"set element tags.md","mtime":1717243362721.9673},{"fname":"Set font size.md","mtime":1705916413562.238},{"fname":"Set laser color.md","mtime":1705916413562.238},{"fname":"Set line angle.md","mtime":1717245410077.0132},{"fname":"Set line length.md","mtime":1717245410077.0132},{"fname":"set link from clipboard.md","mtime":1705650543308.7961},{"fname":"show layer toolbar.md","mtime":1709660698573.6726},{"fname":"show layer toolbar.svg","mtime":1701867705360.2014},{"fname":"show layer.md","mtime":1705907020790.7422},{"fname":"show layers.md","mtime":1705907020790.7422},{"fname":"show outline by frame - kanban.md","mtime":1705650543308.7961},{"fname":"show outline by title level - ex.md","mtime":1705650543308.7961},{"fname":"show outline by title level - kanban.md","mtime":1705650543308.7961},{"fname":"show outline by title level.md","mtime":1705650543308.7961},{"fname":"show thumbnail.md","mtime":1705650543308.7961},{"fname":"Split text by caesura.md","mtime":1705907020790.7422},{"fname":"switch connection shape.md","mtime":1708919956166.2175},{"fname":"switch connection shape.svg","mtime":1706114598416.9868},{"fname":"switch echarts type.md","mtime":1707392712724.2236},{"fname":"text title.md","mtime":1705907020790.7422},{"fname":"Vertical alignment.md","mtime":1705650543308.7961},{"fname":"Vertical distribution.md","mtime":1710738739239.1929},{"fname":"Vertical distribution.svg","mtime":1710738739749.2349},{"fname":"wrap text.md","mtime":1705907020790.7422},{"fname":"_autorun-openfileHook.md","mtime":1707401532804.593},{"fname":"_autorun-utils.md","mtime":1710425396368.1506}]